mt_engines/__init__.py
mt_engines/mt_engines.py
mt_engines-2.0.0.dist-info/LICENSE
mt_engines-2.0.0.dist-info/METADATA
mt_engines-2.0.0.dist-info/WHEEL
mt_engines-2.0.0.dist-info/top_level.txt
mt_engines-2.0.0.dist-info/RECORD
