Metadata-Version: 2.1
Name: mt-engines
Version: 2.0.0
Summary: 机翻引擎
Author: os_linzy
Author-email: 1269125170@gmail.com
Classifier: Programming Language :: Python :: 3
Classifier: License :: OSI Approved :: MIT License
Classifier: Operating System :: OS Independent
Requires-Python: >=3.6
License-File: LICENSE
Requires-Dist: requests
Requires-Dist: tencentcloud-sdk-python-common
Requires-Dist: tencentcloud-sdk-python-tmt
Requires-Dist: pandas
Requires-Dist: deep-translator
